{
  "baseUri": "https://raw.githubusercontent.com/savethekiddes/Daijishou/main/platforms/",
  "platformList": [
    {
      "filename": "title.json",
      "platformName": "☠️ DAIJISHOU HOMEBREW LOADER",
      "platformShortname": "title"
    },
    {
      "filename": "Android.json",
      "platformName": "Android",
      "platformShortname": "android"
    },
    {
      "filename": "Flash.json",
      "platformName": "Flash [EXPERIMENTAL]",
      "platformShortname": "flash"
    },
    {
      "filename": "N64DD.json",
      "platformName": "Nintendo 64 DD",
      "platformShortname": "n64dd"
    },
    {
      "filename": "Retroarch.json",
      "platformName": "Retroarch",
      "platformShortname": "retroarch"
    },
    {
      "filename": "TombRaiderGameEngine.json",
      "platformName": "Tomb Raider Game Engine",
      "platformShortname": "tr"
    }
  ]
}
